{"name":"Voorraadniveau is onder de min (BVA)","id":"voorraadbeheer-voor-autosoort;voorraadniveau-is-onder-de-min-(bva)","testSteps":[{"number":1,"description":"Given Een voorraadniveau die kleiner is dan de minimum peiler","duration":53,"startTime":"2024-11-14T16:56:39.394085500+01:00[Europe/Brussels]","result":"SUCCESS","precondition":false,"level":0},{"number":2,"description":"When Een bestelling wordt geplaatst","duration":1,"startTime":"2024-11-14T16:56:39.449768800+01:00[Europe/Brussels]","result":"SUCCESS","precondition":false,"level":0},{"number":3,"description":"Then zal een foutmelding getoond: \"voorraadniveau moet groter zijn dan de minimum peiler\"","duration":5,"startTime":"2024-11-14T16:56:39.451582600+01:00[Europe/Brussels]","result":"SUCCESS","precondition":false,"level":0}],"userStory":{"id":"voorraadbeheer-voor-autosoort","storyName":"Voorraadbeheer voor autosoort","displayName":"Voorraadbeheer voor autosoort","path":"brainstorm-bijdrage-toevoegen.feature","type":"feature"},"featureTag":{"name":"Voorraadbeheer voor autosoort","type":"feature","displayName":"Voorraadbeheer voor autosoort"},"title":"Voorraadniveau is onder de min (BVA)","description":"","tags":[{"name":"Voorraadbeheer voor autosoort","type":"feature","displayName":"Voorraadbeheer voor autosoort"}],"startTime":"2024-11-14T16:56:39.318128300+01:00[Europe/Brussels]","duration":141,"projectKey":"","isManualTestingUpToDate":false,"manual":false,"testSource":"Cucumber","result":"SUCCESS"}